Metadata-Version: 1.0
Name: atomisator.parser
Version: 0.2.7
Summary: Expert Python Programming - A thin layer on the top of the Universal Feed Parser
Home-page: http://atomisator.ziade.org
Author: Tarek Ziade
Author-email: tarek@ziade.org
License: GPL
Keywords: python best practices
Platform: UNKNOWN
Classifier: Programming Language :: Python
Classifier: Topic :: Software Development :: Libraries :: Python Modules
